scattering_transform/__init__.py
scattering_transform/scattering_transform.py
scattering_transform-0.0.7.dist-info/METADATA
scattering_transform-0.0.7.dist-info/WHEEL
scattering_transform-0.0.7.dist-info/top_level.txt
scattering_transform-0.0.7.dist-info/RECORD
