Metadata-Version: 2.1
Name: scattering-transform
Version: 0.0.7
Summary: Scattering Transform module from the paper Scattering Compositional Learner
Home-page: https://github.com/lucidrains/scattering-compositional-learner
Author: Phil Wang
Author-email: lucidrains@gmail.com
License: MIT
Keywords: artificial intelligence,deep learning,reasoning
Platform: UNKNOWN
Classifier: Development Status :: 4 - Beta
Classifier: Intended Audience :: Developers
Classifier: Topic :: Scientific/Engineering :: Artificial Intelligence
Classifier: License :: OSI Approved :: MIT License
Classifier: Programming Language :: Python :: 3.6
Requires-Dist: torch
